pybincompiler/__init__.py
pybincompiler/__main__.py
pybincompiler/compiler.py
pybincompiler-1.0.0.dist-info/LICENSE
pybincompiler-1.0.0.dist-info/METADATA
pybincompiler-1.0.0.dist-info/WHEEL
pybincompiler-1.0.0.dist-info/entry_points.txt
pybincompiler-1.0.0.dist-info/top_level.txt
pybincompiler-1.0.0.dist-info/RECORD
