Metadata-Version: 2.1
Name: pybincompiler
Version: 1.0.0
Summary: Compiler for binary code to Python
Home-page: https://github.com/JohnYuPromptwSpace/PyBinCompiler
Author: jiwonyu
Author-email: waterflame0221@gmail.com
Classifier: Programming Language :: Python :: 3
Requires-Python: >=3.6
License-File: LICENSE
